[
    {
        "key": "group_5b7c7b1901c1e",
        "title": "Candidate",
        "fields": [
            {
                "key": "field_5b968a60e7bd4",
                "label": "Activated",
                "name": "itjob_cv_activated",
                "type": "true_false",
                "instructions": "",
                "required": 0,
                "conditional_logic": 0,
                "wrapper": {
                    "width": "",
                    "class": "",
                    "id": ""
                },
                "message": "Activé?",
                "default_value": 0,
                "ui": 0,
                "ui_on_text": "",
                "ui_off_text": ""
            },
            {
                "key": "field_5b9c1e4fcd70b",
                "label": "A la une",
                "name": "itjob_cv_featured",
                "type": "true_false",
                "instructions": "",
                "required": 0,
                "conditional_logic": 0,
                "wrapper": {
                    "width": "",
                    "class": "",
                    "id": ""
                },
                "message": "Ajouter pour une candidate à la une",
                "default_value": 0,
                "ui": 0,
                "ui_on_text": "",
                "ui_off_text": ""
            },
            {
                "key": "field_5b7d21e5b18e6",
                "label": "Salutation",
                "name": "itjob_cv_greeting",
                "type": "select",
                "instructions": "",
                "required": 1,
                "conditional_logic": 0,
                "wrapper": {
                    "width": "30",
                    "class": "",
                    "id": ""
                },
                "choices": {
                    "mrs": "Madame",
                    "mr": "Monsieur"
                },
                "default_value": [],
                "allow_null": 0,
                "multiple": 0,
                "ui": 0,
                "ajax": 0,
                "return_format": "array",
                "placeholder": ""
            },
            {
                "key": "field_5b7d22c1dd7b0",
                "label": "Nom",
                "name": "itjob_cv_firstname",
                "type": "text",
                "instructions": "",
                "required": 1,
                "conditional_logic": 0,
                "wrapper": {
                    "width": "60",
                    "class": "",
                    "id": ""
                },
                "default_value": "",
                "placeholder": "Votre nom",
                "prepend": "",
                "append": "",
                "maxlength": ""
            },
            {
                "key": "field_5b7d22e608ba4",
                "label": "Prénom",
                "name": "itjob_cv_lastname",
                "type": "text",
                "instructions": "",
                "required": 1,
                "conditional_logic": 0,
                "wrapper": {
                    "width": "60",
                    "class": "",
                    "id": ""
                },
                "default_value": "",
                "placeholder": "",
                "prepend": "",
                "append": "",
                "maxlength": ""
            },
            {
                "key": "field_5b7e681bd2d28",
                "label": "Email",
                "name": "itjob_cv_email",
                "type": "email",
                "instructions": "",
                "required": 1,
                "conditional_logic": 0,
                "wrapper": {
                    "width": "",
                    "class": "",
                    "id": ""
                },
                "default_value": "",
                "placeholder": "",
                "prepend": "",
                "append": ""
            },
            {
                "key": "field_5b7d230412a17",
                "label": "Adresse",
                "name": "itjob_cv_address",
                "type": "text",
                "instructions": "",
                "required": 1,
                "conditional_logic": 0,
                "wrapper": {
                    "width": "60",
                    "class": "",
                    "id": ""
                },
                "default_value": "",
                "placeholder": "Votre adresse actuelle",
                "prepend": "",
                "append": "",
                "maxlength": ""
            },
            {
                "key": "field_5b7d278408332",
                "label": "Les numéros de téléphone",
                "name": "itjob_cv_phone",
                "type": "repeater",
                "instructions": "",
                "required": 0,
                "conditional_logic": 0,
                "wrapper": {
                    "width": "60",
                    "class": "",
                    "id": ""
                },
                "collapsed": "field_5b7d27b208333",
                "min": 0,
                "max": 0,
                "layout": "table",
                "button_label": "",
                "sub_fields": [
                    {
                        "key": "field_5b7d27b208333",
                        "label": "Numero",
                        "name": "number",
                        "type": "text",
                        "instructions": "",
                        "required": 0,
                        "conditional_logic": 0,
                        "wrapper": {
                            "width": "",
                            "class": "",
                            "id": ""
                        },
                        "default_value": "",
                        "placeholder": "",
                        "prepend": "",
                        "append": "",
                        "maxlength": ""
                    }
                ]
            },
            {
                "key": "field_5b7d288e54fe0",
                "label": "Date de naissance",
                "name": "itjob_cv_birthdayDate",
                "type": "date_picker",
                "instructions": "",
                "required": 1,
                "conditional_logic": 0,
                "wrapper": {
                    "width": "60",
                    "class": "",
                    "id": ""
                },
                "display_format": "m\/d\/Y",
                "return_format": "d-m-Y",
                "first_day": 1
            },
            {
                "key": "field_5b7d28c554fe1",
                "label": "Status",
                "name": "itjob_cv_status",
                "type": "select",
                "instructions": "",
                "required": 1,
                "conditional_logic": 0,
                "wrapper": {
                    "width": "60",
                    "class": "",
                    "id": ""
                },
                "choices": [
                    "Je cherche un emploi",
                    "Je souhaite entretenir mon réseau",
                    "Je cherche un stage"
                ],
                "default_value": [
                    0
                ],
                "allow_null": 0,
                "multiple": 0,
                "ui": 0,
                "ajax": 0,
                "return_format": "array",
                "placeholder": ""
            },
            {
                "key": "field_5b7d2ccf20e5a",
                "label": "Expériences Professionnelles",
                "name": "itjob_cv_experiences",
                "type": "repeater",
                "instructions": "",
                "required": 0,
                "conditional_logic": 0,
                "wrapper": {
                    "width": "",
                    "class": "",
                    "id": ""
                },
                "collapsed": "",
                "min": 0,
                "max": 0,
                "layout": "block",
                "button_label": "Ajouter",
                "sub_fields": [
                    {
                        "key": "field_5b7d2d5720e5b",
                        "label": "Début mois",
                        "name": "exp_dateBegin",
                        "type": "date_picker",
                        "instructions": "",
                        "required": 1,
                        "conditional_logic": 0,
                        "wrapper": {
                            "width": "50",
                            "class": "",
                            "id": ""
                        },
                        "display_format": "F, Y",
                        "return_format": "F, Y",
                        "first_day": 1
                    },
                    {
                        "key": "field_5b7d2dcb20e5c",
                        "label": "Fin mois",
                        "name": "exp_dateEnd",
                        "type": "date_picker",
                        "instructions": "",
                        "required": 0,
                        "conditional_logic": 0,
                        "wrapper": {
                            "width": "50",
                            "class": "",
                            "id": ""
                        },
                        "display_format": "F, Y",
                        "return_format": "F, Y",
                        "first_day": 1
                    },
                    {
                        "key": "field_5b7d2e044733d",
                        "label": "Ville",
                        "name": "exp_city",
                        "type": "text",
                        "instructions": "",
                        "required": 1,
                        "conditional_logic": 0,
                        "wrapper": {
                            "width": "60",
                            "class": "",
                            "id": ""
                        },
                        "default_value": "",
                        "placeholder": "",
                        "prepend": "",
                        "append": "",
                        "maxlength": ""
                    },
                    {
                        "key": "field_5b7d2e4b4733e",
                        "label": "Pays",
                        "name": "exp_country",
                        "type": "text",
                        "instructions": "",
                        "required": 1,
                        "conditional_logic": 0,
                        "wrapper": {
                            "width": "60",
                            "class": "",
                            "id": ""
                        },
                        "default_value": "",
                        "placeholder": "",
                        "prepend": "",
                        "append": "",
                        "maxlength": ""
                    },
                    {
                        "key": "field_5b7d2e754733f",
                        "label": "Nom de l'entreprise ou société",
                        "name": "exp_company",
                        "type": "text",
                        "instructions": "",
                        "required": 1,
                        "conditional_logic": 0,
                        "wrapper": {
                            "width": "60",
                            "class": "",
                            "id": ""
                        },
                        "default_value": "",
                        "placeholder": "",
                        "prepend": "",
                        "append": "",
                        "maxlength": ""
                    },
                    {
                        "key": "field_5b7d2edb47341",
                        "label": "Post occupé",
                        "name": "exp_positionHeld",
                        "type": "text",
                        "instructions": "",
                        "required": 1,
                        "conditional_logic": 0,
                        "wrapper": {
                            "width": "60",
                            "class": "",
                            "id": ""
                        },
                        "default_value": "",
                        "placeholder": "",
                        "prepend": "",
                        "append": "",
                        "maxlength": ""
                    },
                    {
                        "key": "field_5b7d2f327e1dc",
                        "label": "Missions et tâche réalisées",
                        "name": "exp_mission",
                        "type": "wysiwyg",
                        "instructions": "",
                        "required": 0,
                        "conditional_logic": 0,
                        "wrapper": {
                            "width": "",
                            "class": "",
                            "id": ""
                        },
                        "default_value": "",
                        "tabs": "visual",
                        "toolbar": "basic",
                        "media_upload": 1,
                        "delay": 0
                    }
                ]
            },
            {
                "key": "field_5b7d700f01ca3",
                "label": "Formation \/ Diplômes",
                "name": "itjob_cv_trainings",
                "type": "repeater",
                "instructions": "",
                "required": 0,
                "conditional_logic": 0,
                "wrapper": {
                    "width": "",
                    "class": "",
                    "id": ""
                },
                "collapsed": "",
                "min": 0,
                "max": 0,
                "layout": "block",
                "button_label": "Ajouter",
                "sub_fields": [
                    {
                        "key": "field_5b7d76ecbd047",
                        "label": "Date debut",
                        "name": "training_dateBegin",
                        "type": "date_picker",
                        "instructions": "",
                        "required": 1,
                        "conditional_logic": 0,
                        "wrapper": {
                            "width": "50",
                            "class": "",
                            "id": ""
                        },
                        "display_format": "F, Y",
                        "return_format": "F, Y",
                        "first_day": 1
                    },
                    {
                        "key": "field_5b7d774dbd048",
                        "label": "Date fin",
                        "name": "training_dateEnd",
                        "type": "date_picker",
                        "instructions": "",
                        "required": 0,
                        "conditional_logic": 0,
                        "wrapper": {
                            "width": "50",
                            "class": "",
                            "id": ""
                        },
                        "display_format": "F, Y",
                        "return_format": "F, Y",
                        "first_day": 1
                    },
                    {
                        "key": "field_5b7d776ebd049",
                        "label": "Pays",
                        "name": "training_country",
                        "type": "text",
                        "instructions": "",
                        "required": 1,
                        "conditional_logic": 0,
                        "wrapper": {
                            "width": "60",
                            "class": "",
                            "id": ""
                        },
                        "default_value": "",
                        "placeholder": "",
                        "prepend": "",
                        "append": "",
                        "maxlength": ""
                    },
                    {
                        "key": "field_5b7d77e0bd04a",
                        "label": "Ville",
                        "name": "training_city",
                        "type": "text",
                        "instructions": "",
                        "required": 1,
                        "conditional_logic": 0,
                        "wrapper": {
                            "width": "60",
                            "class": "",
                            "id": ""
                        },
                        "default_value": "",
                        "placeholder": "",
                        "prepend": "",
                        "append": "",
                        "maxlength": ""
                    },
                    {
                        "key": "field_5b7d77febd04b",
                        "label": "Diplôme",
                        "name": "training_diploma",
                        "type": "text",
                        "instructions": "",
                        "required": 1,
                        "conditional_logic": 0,
                        "wrapper": {
                            "width": "60",
                            "class": "",
                            "id": ""
                        },
                        "default_value": "",
                        "placeholder": "",
                        "prepend": "",
                        "append": "",
                        "maxlength": ""
                    },
                    {
                        "key": "field_5b7d7879bd04c",
                        "label": "Université\/Ecole",
                        "name": "training_establishment",
                        "type": "text",
                        "instructions": "",
                        "required": 1,
                        "conditional_logic": 0,
                        "wrapper": {
                            "width": "60",
                            "class": "",
                            "id": ""
                        },
                        "default_value": "",
                        "placeholder": "",
                        "prepend": "",
                        "append": "",
                        "maxlength": ""
                    }
                ]
            },
            {
                "key": "field_5b7d293e3f7c2",
                "label": "Permis de conduire",
                "name": "itjob_cv_driveLicence",
                "type": "checkbox",
                "instructions": "",
                "required": 0,
                "conditional_logic": 0,
                "wrapper": {
                    "width": "80",
                    "class": "",
                    "id": ""
                },
                "choices": [
                    "A`",
                    "A",
                    "B",
                    "C",
                    "D"
                ],
                "allow_custom": 0,
                "save_custom": 0,
                "default_value": [],
                "layout": "horizontal",
                "toggle": 0,
                "return_format": "array"
            },
            {
                "key": "field_5b7e69a668dbb",
                "label": "Centre d'intérêt",
                "name": "itjob_cv_centerInterest",
                "type": "group",
                "instructions": "",
                "required": 0,
                "conditional_logic": 0,
                "wrapper": {
                    "width": "",
                    "class": "",
                    "id": ""
                },
                "layout": "table",
                "sub_fields": [
                    {
                        "key": "field_5b7e69f268dbc",
                        "label": "Divers",
                        "name": "various",
                        "type": "text",
                        "instructions": "Les divers sont séparer par virgule.",
                        "required": 0,
                        "conditional_logic": 0,
                        "wrapper": {
                            "width": "70",
                            "class": "",
                            "id": ""
                        },
                        "default_value": "",
                        "placeholder": "ex: Carting, Karaoké...",
                        "prepend": "",
                        "append": "",
                        "maxlength": ""
                    },
                    {
                        "key": "field_5b7e6a2668dbd",
                        "label": "Projet",
                        "name": "projet",
                        "type": "textarea",
                        "instructions": "",
                        "required": 0,
                        "conditional_logic": 0,
                        "wrapper": {
                            "width": "80",
                            "class": "",
                            "id": ""
                        },
                        "default_value": "",
                        "placeholder": "",
                        "maxlength": "",
                        "rows": "",
                        "new_lines": ""
                    }
                ]
            },
            {
                "key": "field_5b7d2c32e15be",
                "label": "Notification Formation",
                "name": "itjob_cv_notifFormation",
                "type": "group",
                "instructions": "",
                "required": 0,
                "conditional_logic": 0,
                "wrapper": {
                    "width": "60",
                    "class": "",
                    "id": ""
                },
                "layout": "table",
                "sub_fields": [
                    {
                        "key": "field_5b7eabca011c2",
                        "label": "Notification",
                        "name": "notification",
                        "type": "true_false",
                        "instructions": "",
                        "required": 0,
                        "conditional_logic": 0,
                        "wrapper": {
                            "width": "",
                            "class": "",
                            "id": ""
                        },
                        "message": "Souhaitez-vous recevoir une notiﬁcation quand une formation est postée sur Itjobmada*",
                        "default_value": 0,
                        "ui": 0,
                        "ui_on_text": "",
                        "ui_off_text": ""
                    },
                    {
                        "key": "field_5b7eabff011c3",
                        "label": "Secteur d'activité",
                        "name": "branch_activity",
                        "type": "taxonomy",
                        "instructions": "Les emplois sont séparer par un virgule.",
                        "required": 0,
                        "conditional_logic": 0,
                        "wrapper": {
                            "width": "",
                            "class": "",
                            "id": ""
                        },
                        "taxonomy": "branch_activity",
                        "field_type": "select",
                        "allow_null": 0,
                        "add_term": 1,
                        "save_terms": 0,
                        "load_terms": 0,
                        "return_format": "object",
                        "multiple": 0
                    }
                ]
            },
            {
                "key": "field_5b7d2ab0e15bd",
                "label": "Notification Emploi",
                "name": "itjob_cv_notifEmploi",
                "type": "group",
                "instructions": "",
                "required": 0,
                "conditional_logic": 0,
                "wrapper": {
                    "width": "60",
                    "class": "",
                    "id": ""
                },
                "layout": "block",
                "sub_fields": [
                    {
                        "key": "field_5b7d805aabd3a",
                        "label": "Recevoir de notification?",
                        "name": "notification",
                        "type": "true_false",
                        "instructions": "Souhaitez-vous recevoir une notiﬁcation\r\nquand une offre d’emploi est postée sur Itjobmada",
                        "required": 0,
                        "conditional_logic": 0,
                        "wrapper": {
                            "width": "",
                            "class": "",
                            "id": ""
                        },
                        "message": "Souhaitez-vous recevoir une notiﬁcation?",
                        "default_value": 0,
                        "ui": 0,
                        "ui_on_text": "",
                        "ui_off_text": ""
                    },
                    {
                        "key": "field_5b7d80ff8a16b",
                        "label": "Secteur d'activité",
                        "name": "branch_activity",
                        "type": "taxonomy",
                        "instructions": "Recevoir une notiﬁcation pour quel emploi ?",
                        "required": 0,
                        "conditional_logic": [
                            [
                                {
                                    "field": "field_5b7d805aabd3a",
                                    "operator": "==",
                                    "value": "1"
                                }
                            ]
                        ],
                        "wrapper": {
                            "width": "50",
                            "class": "",
                            "id": ""
                        },
                        "taxonomy": "branch_activity",
                        "field_type": "select",
                        "allow_null": 1,
                        "add_term": 0,
                        "save_terms": 0,
                        "load_terms": 0,
                        "return_format": "object",
                        "multiple": 0
                    },
                    {
                        "key": "field_5b7d81368a16c",
                        "label": "Mot clé",
                        "name": "job_sought",
                        "type": "text",
                        "instructions": "Les mots clé sont séparer avec les virgules",
                        "required": 0,
                        "conditional_logic": [
                            [
                                {
                                    "field": "field_5b7d805aabd3a",
                                    "operator": "==",
                                    "value": "1"
                                }
                            ]
                        ],
                        "wrapper": {
                            "width": "",
                            "class": "",
                            "id": ""
                        },
                        "default_value": "",
                        "placeholder": "Ajouter mot clé",
                        "prepend": "",
                        "append": "",
                        "maxlength": ""
                    }
                ]
            },
            {
                "key": "field_5b7d7b5ea6046",
                "label": "Newsletter",
                "name": "itjob_cv_newsletter",
                "type": "true_false",
                "instructions": "",
                "required": 0,
                "conditional_logic": 0,
                "wrapper": {
                    "width": "60",
                    "class": "",
                    "id": ""
                },
                "message": "Est ce que vous voulez recevoir notre newsletter?",
                "default_value": 0,
                "ui": 0,
                "ui_on_text": "",
                "ui_off_text": ""
            },
            {
                "key": "field_5ba6477ee5218",
                "label": "Les offers postulé",
                "name": "itjob_cv_offer_apply",
                "type": "post_object",
                "instructions": "",
                "required": 0,
                "conditional_logic": 0,
                "wrapper": {
                    "width": "",
                    "class": "",
                    "id": ""
                },
                "post_type": [
                    "offers"
                ],
                "taxonomy": [],
                "allow_null": 0,
                "multiple": 1,
                "return_format": "id",
                "ui": 1
            }
        ],
        "location": [
            [
                {
                    "param": "post_type",
                    "operator": "==",
                    "value": "candidate"
                }
            ]
        ],
        "menu_order": 0,
        "position": "normal",
        "style": "default",
        "label_placement": "top",
        "instruction_placement": "label",
        "hide_on_screen": "",
        "active": 1,
        "description": ""
    },
    {
        "key": "group_5b788bd890336",
        "title": "Company",
        "fields": [
            {
                "key": "field_5b7897cc9cb4c",
                "label": "Adresse de l'entreprise",
                "name": "itjob_company_address",
                "type": "text",
                "instructions": "",
                "required": 1,
                "conditional_logic": 0,
                "wrapper": {
                    "width": "60",
                    "class": "",
                    "id": ""
                },
                "default_value": "",
                "placeholder": "",
                "prepend": "",
                "append": "",
                "maxlength": ""
            },
            {
                "key": "field_5b7897e69cb4d",
                "label": "NIF",
                "name": "itjob_company_nif",
                "type": "text",
                "instructions": "",
                "required": 1,
                "conditional_logic": 0,
                "wrapper": {
                    "width": "60",
                    "class": "",
                    "id": ""
                },
                "default_value": 0,
                "placeholder": "Numéro d'Identification Fiscale",
                "prepend": "",
                "append": "",
                "maxlength": ""
            },
            {
                "key": "field_5b789835edc95",
                "label": "Numéro statistique",
                "name": "itjob_company_stat",
                "type": "text",
                "instructions": "",
                "required": 1,
                "conditional_logic": 0,
                "wrapper": {
                    "width": "60",
                    "class": "",
                    "id": ""
                },
                "default_value": 0,
                "placeholder": "",
                "prepend": "",
                "append": "",
                "maxlength": ""
            },
            {
                "key": "field_5b78985d33470",
                "label": "Téléphone mobile du responsable",
                "name": "itjob_company_cellphone",
                "type": "repeater",
                "instructions": "",
                "required": 1,
                "conditional_logic": 0,
                "wrapper": {
                    "width": "100",
                    "class": "",
                    "id": ""
                },
                "collapsed": "",
                "min": 0,
                "max": 0,
                "layout": "table",
                "button_label": "",
                "sub_fields": [
                    {
                        "key": "field_5b78987f33471",
                        "label": "Phone",
                        "name": "number",
                        "type": "text",
                        "instructions": "",
                        "required": 0,
                        "conditional_logic": 0,
                        "wrapper": {
                            "width": "",
                            "class": "",
                            "id": ""
                        },
                        "default_value": "",
                        "placeholder": "",
                        "prepend": "",
                        "append": "",
                        "maxlength": ""
                    }
                ]
            },
            {
                "key": "field_5b83da1dc08bf",
                "label": "Téléphone Fix",
                "name": "itjob_company_phone",
                "type": "text",
                "instructions": "",
                "required": 0,
                "conditional_logic": 0,
                "wrapper": {
                    "width": "",
                    "class": "",
                    "id": ""
                },
                "default_value": "",
                "placeholder": "",
                "prepend": "",
                "append": "",
                "maxlength": ""
            },
            {
                "key": "field_5b81cba9e237f",
                "label": "Salutation",
                "name": "itjob_company_greeting",
                "type": "select",
                "instructions": "",
                "required": 1,
                "conditional_logic": 0,
                "wrapper": {
                    "width": "30",
                    "class": "",
                    "id": ""
                },
                "choices": {
                    "mrs": "Madame",
                    "mr": "Monsieur"
                },
                "default_value": [
                    "mr"
                ],
                "allow_null": 0,
                "multiple": 0,
                "ui": 0,
                "ajax": 0,
                "return_format": "value",
                "placeholder": ""
            },
            {
                "key": "field_5b81cb05e237d",
                "label": "Nom & Prénom",
                "name": "itjob_company_name",
                "type": "text",
                "instructions": "",
                "required": 1,
                "conditional_logic": 0,
                "wrapper": {
                    "width": "70",
                    "class": "",
                    "id": ""
                },
                "default_value": "",
                "placeholder": "",
                "prepend": "",
                "append": "",
                "maxlength": ""
            },
            {
                "key": "field_5b7899101a658",
                "label": "Adresse email",
                "name": "itjob_company_email",
                "type": "text",
                "instructions": "",
                "required": 1,
                "conditional_logic": 0,
                "wrapper": {
                    "width": "60",
                    "class": "",
                    "id": ""
                },
                "default_value": "",
                "placeholder": "",
                "prepend": "",
                "append": "",
                "maxlength": ""
            },
            {
                "key": "field_5b78993e13dd6",
                "label": "Newsletter",
                "name": "itjob_company_newsletter",
                "type": "true_false",
                "instructions": "",
                "required": 0,
                "conditional_logic": 0,
                "wrapper": {
                    "width": "",
                    "class": "",
                    "id": ""
                },
                "message": "Est ce que vous voulez recevoir notre newsletter?",
                "default_value": 0,
                "ui": 0,
                "ui_on_text": "",
                "ui_off_text": ""
            },
            {
                "key": "field_5b7899b813dd7",
                "label": "Notification",
                "name": "itjob_company_notification",
                "type": "true_false",
                "instructions": "",
                "required": 0,
                "conditional_logic": 0,
                "wrapper": {
                    "width": "",
                    "class": "",
                    "id": ""
                },
                "message": "Souhaitez-vous recevoir une notiﬁcation quand un nouveau CV est insérer dans Itjobmada?",
                "default_value": 0,
                "ui": 0,
                "ui_on_text": "",
                "ui_off_text": ""
            }
        ],
        "location": [
            [
                {
                    "param": "post_type",
                    "operator": "==",
                    "value": "company"
                }
            ]
        ],
        "menu_order": 0,
        "position": "normal",
        "style": "default",
        "label_placement": "top",
        "instruction_placement": "label",
        "hide_on_screen": "",
        "active": 1,
        "description": ""
    },
    {
        "key": "group_5b7886315b8b9",
        "title": "Offres",
        "fields": [
            {
                "key": "field_5b8904a232984",
                "label": "Poste à promouvoir",
                "name": "itjob_offer_post",
                "type": "text",
                "instructions": "Ce champ est égale au titre de l'article",
                "required": 1,
                "conditional_logic": 0,
                "wrapper": {
                    "width": "60",
                    "class": "",
                    "id": ""
                },
                "default_value": "",
                "placeholder": "",
                "prepend": "",
                "append": "",
                "maxlength": ""
            },
            {
                "key": "field_5b788a40dcbf9",
                "label": "A la une",
                "name": "itjob_offer_featured",
                "type": "true_false",
                "instructions": "",
                "required": 0,
                "conditional_logic": 0,
                "wrapper": {
                    "width": "",
                    "class": "",
                    "id": ""
                },
                "message": "Ajouter pour une annonce à la une",
                "default_value": 0,
                "ui": 0,
                "ui_on_text": "",
                "ui_off_text": ""
            },
            {
                "key": "field_5b78865a958fd",
                "label": "Référence",
                "name": "itjob_offer_reference",
                "type": "text",
                "instructions": "Ce champ est généré automatiquement par un algorithme.",
                "required": 0,
                "conditional_logic": 0,
                "wrapper": {
                    "width": "50",
                    "class": "",
                    "id": ""
                },
                "default_value": "",
                "placeholder": "Ce champ est généré automatiquement par un algorithme.",
                "prepend": "",
                "append": "",
                "maxlength": ""
            },
            {
                "key": "field_5b7886ac958fe",
                "label": "Date limite de candidature",
                "name": "itjob_offer_datelimit",
                "type": "date_picker",
                "instructions": "",
                "required": 1,
                "conditional_logic": 0,
                "wrapper": {
                    "width": "50",
                    "class": "",
                    "id": ""
                },
                "display_format": "m\/d\/Y",
                "return_format": "m\/d\/Y",
                "first_day": 1
            },
            {
                "key": "field_5b78879454dc1",
                "label": "Type de contrat",
                "name": "itjob_offer_contrattype",
                "type": "select",
                "instructions": "",
                "required": 1,
                "conditional_logic": 0,
                "wrapper": {
                    "width": "50",
                    "class": "",
                    "id": ""
                },
                "choices": {
                    "cdd": "CDD",
                    "cdi": "CDI"
                },
                "default_value": [],
                "allow_null": 1,
                "multiple": 0,
                "ui": 0,
                "ajax": 0,
                "return_format": "array",
                "placeholder": ""
            },
            {
                "key": "field_5b788908b1dab",
                "label": "Profil recherché",
                "name": "itjob_offer_profil",
                "type": "wysiwyg",
                "instructions": "",
                "required": 1,
                "conditional_logic": 0,
                "wrapper": {
                    "width": "60",
                    "class": "",
                    "id": ""
                },
                "default_value": "",
                "tabs": "visual",
                "toolbar": "basic",
                "media_upload": 1,
                "delay": 0
            },
            {
                "key": "field_5b7889644ef8f",
                "label": "Mission",
                "name": "itjob_offer_mission",
                "type": "wysiwyg",
                "instructions": "",
                "required": 1,
                "conditional_logic": 0,
                "wrapper": {
                    "width": "60",
                    "class": "",
                    "id": ""
                },
                "default_value": "",
                "tabs": "visual",
                "toolbar": "basic",
                "media_upload": 1,
                "delay": 0
            },
            {
                "key": "field_5b78899ddd18a",
                "label": "Salaire proposé",
                "name": "itjob_offer_proposedsallary",
                "type": "number",
                "instructions": "",
                "required": 1,
                "conditional_logic": 0,
                "wrapper": {
                    "width": "60",
                    "class": "",
                    "id": ""
                },
                "default_value": 0,
                "placeholder": "Salaire net",
                "prepend": "",
                "append": "",
                "min": "",
                "max": "",
                "step": 100
            },
            {
                "key": "field_5b788a1bdcbf8",
                "label": "Autres informations",
                "name": "itjob_offer_otherinformation",
                "type": "wysiwyg",
                "instructions": "",
                "required": 0,
                "conditional_logic": 0,
                "wrapper": {
                    "width": "60",
                    "class": "",
                    "id": ""
                },
                "default_value": "",
                "tabs": "all",
                "toolbar": "basic",
                "media_upload": 1,
                "delay": 0
            },
            {
                "key": "field_5b788a8e136ef",
                "label": "Souhaite que l'annonce apparaisse à",
                "name": "itjob_offer_locationcible",
                "type": "taxonomy",
                "instructions": "Laisser vide pour prendre en compte tout les région.",
                "required": 0,
                "conditional_logic": 0,
                "wrapper": {
                    "width": "",
                    "class": "",
                    "id": ""
                },
                "taxonomy": "region",
                "field_type": "checkbox",
                "allow_null": 1,
                "add_term": 1,
                "save_terms": 0,
                "load_terms": 0,
                "return_format": "object",
                "multiple": 0
            },
            {
                "key": "field_5b7c8825d7cfb",
                "label": "Entreprise",
                "name": "itjob_offer_company",
                "type": "post_object",
                "instructions": "",
                "required": 1,
                "conditional_logic": 0,
                "wrapper": {
                    "width": "60",
                    "class": "",
                    "id": ""
                },
                "post_type": [
                    "company"
                ],
                "taxonomy": [],
                "allow_null": 0,
                "multiple": 0,
                "return_format": "object",
                "ui": 1
            },
            {
                "key": "field_5b87159acf7cb",
                "label": "Secteur d'activité",
                "name": "itjob_offer_abranch",
                "type": "taxonomy",
                "instructions": "",
                "required": 1,
                "conditional_logic": 0,
                "wrapper": {
                    "width": "60",
                    "class": "",
                    "id": ""
                },
                "taxonomy": "branch_activity",
                "field_type": "select",
                "allow_null": 0,
                "add_term": 0,
                "save_terms": 0,
                "load_terms": 0,
                "return_format": "object",
                "multiple": 0
            },
            {
                "key": "field_5ba647e4a9e8c",
                "label": "Les utilisateurs qui ont postulé",
                "name": "itjob_users_apply",
                "type": "user",
                "instructions": "",
                "required": 0,
                "conditional_logic": 0,
                "wrapper": {
                    "width": "",
                    "class": "",
                    "id": ""
                },
                "role": "",
                "allow_null": 0,
                "multiple": 1,
                "return_format": "id"
            }
        ],
        "location": [
            [
                {
                    "param": "post_type",
                    "operator": "==",
                    "value": "offers"
                }
            ]
        ],
        "menu_order": 0,
        "position": "normal",
        "style": "default",
        "label_placement": "top",
        "instruction_placement": "label",
        "hide_on_screen": "",
        "active": 1,
        "description": ""
    },
    {
        "key": "group_5b891e91bca5f",
        "title": "Options",
        "fields": [
            {
                "key": "field_5b891ea2f960a",
                "label": "Page de connexion",
                "name": "login_page_id",
                "type": "post_object",
                "instructions": "Ajouter ici la page pour se connecter",
                "required": 1,
                "conditional_logic": 0,
                "wrapper": {
                    "width": "50",
                    "class": "",
                    "id": ""
                },
                "post_type": [
                    "page",
                    "post"
                ],
                "taxonomy": [],
                "allow_null": 0,
                "multiple": 0,
                "return_format": "id",
                "ui": 1
            },
            {
                "key": "field_5b89200e21ff2",
                "label": "Espace client",
                "name": "espace_client",
                "type": "post_object",
                "instructions": "La page pour l'espace client",
                "required": 1,
                "conditional_logic": 0,
                "wrapper": {
                    "width": "50",
                    "class": "",
                    "id": ""
                },
                "post_type": [
                    "page"
                ],
                "taxonomy": [],
                "allow_null": 0,
                "multiple": 0,
                "return_format": "id",
                "ui": 1
            },
            {
                "key": "field_5b89215bdbfbb",
                "label": "Page d'enregistrement",
                "name": "register_page_id",
                "type": "post_object",
                "instructions": "",
                "required": 1,
                "conditional_logic": 0,
                "wrapper": {
                    "width": "50",
                    "class": "",
                    "id": ""
                },
                "post_type": [
                    "page",
                    "post"
                ],
                "taxonomy": [],
                "allow_null": 0,
                "multiple": 0,
                "return_format": "id",
                "ui": 1
            },
            {
                "key": "field_5b8923bf1b6a4",
                "label": "Formulaire d'ajoute",
                "name": "",
                "type": "message",
                "instructions": "",
                "required": 0,
                "conditional_logic": 0,
                "wrapper": {
                    "width": "",
                    "class": "",
                    "id": ""
                },
                "message": "Ci-joint les formulaires d'ajout.",
                "new_lines": "wpautop",
                "esc_html": 0
            },
            {
                "key": "field_5b892415d4bf6",
                "label": "Page d'ajout d'offre",
                "name": "add_offer_page_id",
                "type": "post_object",
                "instructions": "",
                "required": 1,
                "conditional_logic": 0,
                "wrapper": {
                    "width": "50",
                    "class": "",
                    "id": ""
                },
                "post_type": [
                    "page"
                ],
                "taxonomy": [],
                "allow_null": 0,
                "multiple": 0,
                "return_format": "id",
                "ui": 1
            },
            {
                "key": "field_5b892448d4bf7",
                "label": "Page d'ajout d'un utilisateur (Entreprise)",
                "name": "register_company_page_id",
                "type": "post_object",
                "instructions": "",
                "required": 0,
                "conditional_logic": 0,
                "wrapper": {
                    "width": "50",
                    "class": "",
                    "id": ""
                },
                "post_type": [
                    "page"
                ],
                "taxonomy": [],
                "allow_null": 0,
                "multiple": 0,
                "return_format": "id",
                "ui": 1
            },
            {
                "key": "field_5b95813888a8a",
                "label": "Page d'ajout d'un utilisateur (Particulier)",
                "name": "register_particular_page_id",
                "type": "post_object",
                "instructions": "",
                "required": 0,
                "conditional_logic": 0,
                "wrapper": {
                    "width": "50",
                    "class": "",
                    "id": ""
                },
                "post_type": [
                    "page"
                ],
                "taxonomy": [],
                "allow_null": 0,
                "multiple": 0,
                "return_format": "id",
                "ui": 1
            },
            {
                "key": "field_5b997076cbf7d",
                "label": "Page d'ajout d'un utilisateur (Candidat)",
                "name": "register_candidate_page_id",
                "type": "post_object",
                "instructions": "",
                "required": 0,
                "conditional_logic": 0,
                "wrapper": {
                    "width": "50",
                    "class": "",
                    "id": ""
                },
                "post_type": [
                    "page"
                ],
                "taxonomy": [],
                "allow_null": 0,
                "multiple": 0,
                "return_format": "id",
                "ui": 1
            }
        ],
        "location": [
            [
                {
                    "param": "options_page",
                    "operator": "==",
                    "value": "acf-options-itjob-settings"
                }
            ]
        ],
        "menu_order": 0,
        "position": "normal",
        "style": "default",
        "label_placement": "top",
        "instruction_placement": "label",
        "hide_on_screen": "",
        "active": 1,
        "description": ""
    },
    {
        "key": "group_5ba6257b5bc2a",
        "title": "Terms",
        "fields": [
            {
                "key": "field_5ba62905d3eef",
                "label": "Visible dans le site",
                "name": "activated",
                "type": "true_false",
                "instructions": "",
                "required": 0,
                "conditional_logic": 0,
                "wrapper": {
                    "width": "",
                    "class": "",
                    "id": ""
                },
                "message": "Rendre cette term visible",
                "default_value": 0,
                "ui": 0,
                "ui_on_text": "",
                "ui_off_text": ""
            }
        ],
        "location": [
            [
                {
                    "param": "taxonomy",
                    "operator": "==",
                    "value": "all"
                }
            ]
        ],
        "menu_order": 0,
        "position": "acf_after_title",
        "style": "default",
        "label_placement": "top",
        "instruction_placement": "label",
        "hide_on_screen": "",
        "active": 1,
        "description": ""
    }
]